nn_info/__init__.py
nn_info/estimators.py
nn_info/theory.py
nn_info-0.0.7.dist-info/METADATA
nn_info-0.0.7.dist-info/WHEEL
nn_info-0.0.7.dist-info/licenses/LICENSE
nn_info-0.0.7.dist-info/RECORD
