Metadata-Version: 2.1
Name: nn_info
Version: 0.0.7
Summary: nearest neighbor based estimators for measures of information theory
Project-URL: Homepage, https://github.com/zuiop11/nn_info
Project-URL: Bug Tracker, https://github.com/zuiop11/nn_info
Author-email: Bettina Schmidt <bettina.schmidt@charite.de>
License-File: LICENSE
Classifier: License :: OSI Approved :: MIT License
Classifier: Operating System :: OS Independent
Classifier: Programming Language :: Python :: 3
Requires-Python: >=3.7
